z3kural/__init__.py
z3kural/core.py
z3kural/kural.json
z3kural-0.1.1.dist-info/LICENSE
z3kural-0.1.1.dist-info/METADATA
z3kural-0.1.1.dist-info/WHEEL
z3kural-0.1.1.dist-info/top_level.txt
z3kural-0.1.1.dist-info/RECORD
