Metadata-Version: 2.2
Name: z3kural
Version: 0.1.1
Summary: A Python package to fetch Thirukkural verses
Home-page: https://github.com/z3connect/z3kural
Author: Z3Connect
Author-email: z3connect.z3connect@gmail.com
Classifier: Programming Language :: Python :: 3
Classifier: License :: OSI Approved :: MIT License
Classifier: Operating System :: OS Independent
Requires-Python: >=3.6
License-File: LICENSE
Dynamic: author
Dynamic: author-email
Dynamic: classifier
Dynamic: description
Dynamic: description-content-type
Dynamic: home-page
Dynamic: requires-python
Dynamic: summary
